odoo8_addon_account_move_batch_validate-8.0.0.2.0.99.dev18-py2.7-nspkg.pth
odoo8_addon_account_move_batch_validate-8.0.0.2.0.99.dev18.dist-info/METADATA
odoo8_addon_account_move_batch_validate-8.0.0.2.0.99.dev18.dist-info/RECORD
odoo8_addon_account_move_batch_validate-8.0.0.2.0.99.dev18.dist-info/WHEEL
odoo8_addon_account_move_batch_validate-8.0.0.2.0.99.dev18.dist-info/namespace_packages.txt
odoo8_addon_account_move_batch_validate-8.0.0.2.0.99.dev18.dist-info/top_level.txt
odoo_addons/account_move_batch_validate/README.rst
odoo_addons/account_move_batch_validate/__init__.py
odoo_addons/account_move_batch_validate/__openerp__.py
odoo_addons/account_move_batch_validate/account.py
odoo_addons/account_move_batch_validate/account_view.xml
odoo_addons/account_move_batch_validate/i18n/account_move_batch_validate.pot
odoo_addons/account_move_batch_validate/i18n/am.po
odoo_addons/account_move_batch_validate/i18n/ar.po
odoo_addons/account_move_batch_validate/i18n/bg.po
odoo_addons/account_move_batch_validate/i18n/bs.po
odoo_addons/account_move_batch_validate/i18n/ca.po
odoo_addons/account_move_batch_validate/i18n/ca_ES.po
odoo_addons/account_move_batch_validate/i18n/cs.po
odoo_addons/account_move_batch_validate/i18n/de.po
odoo_addons/account_move_batch_validate/i18n/en_GB.po
odoo_addons/account_move_batch_validate/i18n/es.po
odoo_addons/account_move_batch_validate/i18n/es_CR.po
odoo_addons/account_move_batch_validate/i18n/es_EC.po
odoo_addons/account_move_batch_validate/i18n/es_ES.po
odoo_addons/account_move_batch_validate/i18n/es_MX.po
odoo_addons/account_move_batch_validate/i18n/es_VE.po
odoo_addons/account_move_batch_validate/i18n/et.po
odoo_addons/account_move_batch_validate/i18n/fi.po
odoo_addons/account_move_batch_validate/i18n/fr.po
odoo_addons/account_move_batch_validate/i18n/gl.po
odoo_addons/account_move_batch_validate/i18n/gl_ES.po
odoo_addons/account_move_batch_validate/i18n/gu.po
odoo_addons/account_move_batch_validate/i18n/hr.po
odoo_addons/account_move_batch_validate/i18n/hr_HR.po
odoo_addons/account_move_batch_validate/i18n/hu.po
odoo_addons/account_move_batch_validate/i18n/id.po
odoo_addons/account_move_batch_validate/i18n/it.po
odoo_addons/account_move_batch_validate/i18n/ja.po
odoo_addons/account_move_batch_validate/i18n/lt.po
odoo_addons/account_move_batch_validate/i18n/mk.po
