Metadata-Version: 2.1
Name: odoo8-addon-account-move-batch-validate
Version: 8.0.0.2.0.99.dev18
Summary: Account Move Batch Validate
Home-page: http://www.camptocamp.com
Author: Camptocamp,Odoo Community Association (OCA)
Author-email: support@odoo-community.org
License: AGPL-3
Platform: UNKNOWN
Classifier: Programming Language :: Python
Classifier: Framework :: Odoo
Classifier: License :: OSI Approved :: GNU Affero General Public License v3
Requires-Python: ~=2.7
Requires-Dist: odoo8-addon-account-default-draft-move
Requires-Dist: odoo8-addon-connector
Requires-Dist: odoo (<9.0a,>=8.0a)
